pyauthenticator/__init__.py
pyauthenticator/__main__.py
pyauthenticator/_cmd.py
pyauthenticator/_config.py
pyauthenticator/_core.py
pyauthenticator/_user.py
pyauthenticator/_version.py
pyauthenticator/api.py
pyauthenticator-0.3.0.dist-info/METADATA
pyauthenticator-0.3.0.dist-info/WHEEL
pyauthenticator-0.3.0.dist-info/entry_points.txt
pyauthenticator-0.3.0.dist-info/licenses/LICENSE
pyauthenticator-0.3.0.dist-info/RECORD
