Metadata-Version: 2.4
Name: pyauthenticator
Version: 0.3.0
Summary: Similar to the Google authenticator just written in python.
Project-URL: Homepage, https://github.com/jan-janssen/pyauthenticator
Project-URL: Documentation, https://github.com/jan-janssen/pyauthenticator/blob/master/README.md
Project-URL: Source, https://github.com/jan-janssen/pyauthenticator
Project-URL: Tracker, https://github.com/jan-janssen/pyauthenticator/issues
Author-email: Jan Janssen <jan.janssen@outlook.com>
License: BSD-3-Clause
License-File: LICENSE
Keywords: 2FA,MFA,authenticator
Classifier: Development Status :: 5 - Production/Stable
Classifier: Intended Audience :: Developers
Classifier: License :: OSI Approved :: BSD License
Classifier: Operating System :: OS Independent
Classifier: Programming Language :: Python :: 3
Classifier: Programming Language :: Python :: 3.7
Classifier: Programming Language :: Python :: 3.8
Classifier: Programming Language :: Python :: 3.9
Classifier: Programming Language :: Python :: 3.10
Classifier: Programming Language :: Python :: 3.11
Classifier: Programming Language :: Python :: 3.12
Classifier: Programming Language :: Python :: 3.13
Classifier: Topic :: Security
Classifier: Topic :: Utilities
Requires-Python: >=3.7
Requires-Dist: pillow>=11.3.0
Requires-Dist: pyotp>=2.9.0
Requires-Dist: pyzbar>=0.1.9
Requires-Dist: qrcode>=8.2
